cardinality_cs110/__init__.py
cardinality_cs110/__main__.py
cardinality_cs110-0.0.9.dist-info/LICENSE.txt
cardinality_cs110-0.0.9.dist-info/METADATA
cardinality_cs110-0.0.9.dist-info/WHEEL
cardinality_cs110-0.0.9.dist-info/top_level.txt
cardinality_cs110-0.0.9.dist-info/RECORD
