Metadata-Version: 2.1
Name: cardinality-cs110
Version: 0.0.9
Summary: A cardinality estimator using the Flajolet-Martin algorithm
Home-page: https://github.com/DarthQadir/cardinality_cs110.git
Author: Abdul Qadir
Author-email: abdul.qadir@minerva.kgi
License: UNKNOWN
Platform: UNKNOWN
Classifier: Programming Language :: Python :: 3
Classifier: License :: OSI Approved :: MIT License
Classifier: Operating System :: OS Independent
